Metadata-Version: 2.1
Name: odoo14-addon-sale_stock_line_sequence
Version: 14.0.1.0.1.dev6
Summary: Glue Module for Sale Order Line Sequence and Stock Picking Line Sequence
Home-page: https://github.com/OCA/sale-workflow
Author: ForgeFlow, Odoo Community Association (OCA)
Author-email: support@odoo-community.org
License: AGPL-3
Classifier: Programming Language :: Python
Classifier: Framework :: Odoo
Classifier: Framework :: Odoo :: 14.0
Classifier: License :: OSI Approved :: GNU Affero General Public License v3
Requires-Python: >=3.6
Requires-Dist: odoo14-addon-sale-order-line-sequence
Requires-Dist: odoo14-addon-stock-picking-line-sequence
Requires-Dist: odoo<14.1dev,>=14.0a
